dictkit/__init__.py
dictkit/categorize.py
dictkit/render.py
dictkit/utildict.py
dictkit-0.1.6.dist-info/METADATA
dictkit-0.1.6.dist-info/WHEEL
dictkit-0.1.6.dist-info/RECORD
