Metadata-Version: 2.1
Name: dictkit
Version: 0.1.6
Summary: Utility data structures with simple but powerful features.
Author-email: Ryan Young <dev@ryayoung.com>
Classifier: Development Status :: 3 - Alpha
Classifier: Intended Audience :: Developers
Classifier: License :: OSI Approved :: MIT License
Classifier: Operating System :: OS Independent
Classifier: Programming Language :: Python :: 3.11
Classifier: Topic :: Software Development :: Libraries
